<annotation>
	<folder></folder>
	<filename>2bath_4229_jpg.rf.f31154ea0a78719eb4858c1b2cc67892.jpg</filename>
	<path>2bath_4229_jpg.rf.f31154ea0a78719eb4858c1b2cc67892.jpg</path>
	<source>
		<database>roboflow.com</database>
	</source>
	<size>
		<width>640</width>
		<height>640</height>
		<depth>3</depth>
	</size>
	<segmented>0</segmented>
	<object>
		<name>2 Bath</name>
		<pose>Unspecified</pose>
		<truncated>0</truncated>
		<difficult>0</difficult>
		<occluded>0</occluded>
		<bndbox>
			<xmin>196</xmin>
			<xmax>420</xmax>
			<ymin>300</ymin>
			<ymax>460</ymax>
		</bndbox>
	</object>
</annotation>
